flask_pyngrok
