Metadata-Version: 2.1
Name: Flask-PyNgrok
Version: 1.0.3
Summary: Add tunneling support to your Flask Application.
Home-page: https://github.com/sidshrivastav/Flask-PyNgrok
Author: Siddhant Shrivastav
Author-email: siddhantshrivastava@outlook.com
License: MIT
Platform: any
Classifier: Environment :: Web Environment
Classifier: Intended Audience :: Developers
Classifier: License :: OSI Approved :: BSD License
Classifier: Operating System :: OS Independent
Classifier: Programming Language :: Python
Classifier: Topic :: Internet :: WWW/HTTP :: Dynamic Content
Classifier: Topic :: Software Development :: Libraries :: Python Modules
